Metadata-Version: 2.4
Name: simpletransformers
Version: 0.70.3
Summary: An easy-to-use wrapper library for the Transformers library.
Home-page: https://github.com/ThilinaRajapakse/simpletransformers/
Author: Thilina Rajapakse
Author-email: chaturangarajapakshe@gmail.com
Classifier: Intended Audience :: Science/Research
Classifier: License :: OSI Approved :: Apache Software License
Classifier: Programming Language :: Python :: 3
Classifier: Topic :: Scientific/Engineering :: Artificial Intelligence
Requires-Python: >=3.6
License-File: LICENSE
Requires-Dist: numpy
Requires-Dist: requests
Requires-Dist: tqdm>=4.47.0
Requires-Dist: regex
Requires-Dist: transformers>=4.31.0
Requires-Dist: datasets
Requires-Dist: scipy
Requires-Dist: scikit-learn
Requires-Dist: seqeval
Requires-Dist: tensorboard
Requires-Dist: tensorboardx
Requires-Dist: pandas
Requires-Dist: tokenizers
Requires-Dist: wandb>=0.10.32
Requires-Dist: streamlit
Requires-Dist: sentencepiece
Dynamic: author
Dynamic: author-email
Dynamic: classifier
Dynamic: description
Dynamic: description-content-type
Dynamic: home-page
Dynamic: license-file
Dynamic: requires-dist
Dynamic: requires-python
Dynamic: summary
